README.rst
requirements.txt
requirements_doc.txt
requirements_gui.txt
requirements_test.txt
setup.cfg
setup.py
logo/odMLtables.eps
logo/odMLtables.pdf
logo/odMLtables.png
logo/odMLtables.svg
logo/odMLtables_100x100.png
odmltables/VERSION.txt
odmltables/__init__.py
odmltables/compare_section_csv_table.py
odmltables/compare_section_table.py
odmltables/compare_section_xls_table.py
odmltables/create_examples.py
odmltables/odml_csv_table.py
odmltables/odml_table.py
odmltables/odml_xls_table.py
odmltables/xls_style.py
odmltables.egg-info/PKG-INFO
odmltables.egg-info/SOURCES.txt
odmltables.egg-info/dependency_links.txt
odmltables.egg-info/entry_points.txt
odmltables.egg-info/not-zip-safe
odmltables.egg-info/requires.txt
odmltables.egg-info/top_level.txt
odmltables/gui/__init__.py
odmltables/gui/compsectionpages.py
odmltables/gui/compsectionwiz.py
odmltables/gui/converterpages.py
odmltables/gui/converterwiz.py
odmltables/gui/filterpages.py
odmltables/gui/filterwiz.py
odmltables/gui/filterwiz2.0.py
odmltables/gui/generatetemplatepages.py
odmltables/gui/generatetemplatewiz.py
odmltables/gui/main.py
odmltables/gui/mainwindow.py
odmltables/gui/mergepages.py
odmltables/gui/mergewiz.py
odmltables/gui/mergewiz2.0.py
odmltables/gui/pageutils.py
odmltables/gui/settings.py
odmltables/gui/wizutils.py
odmltables/gui/graphics/comparetable.aux
odmltables/gui/graphics/comparetable.dvi
odmltables/gui/graphics/comparetable.log
odmltables/gui/graphics/comparetable.pdf
odmltables/gui/graphics/comparetable.ps
odmltables/gui/graphics/comparetable.svg
odmltables/gui/graphics/comparetable.tex
odmltables/gui/graphics/comparetable.tex.backup
odmltables/gui/graphics/convertodml.aux
odmltables/gui/graphics/convertodml.dvi
odmltables/gui/graphics/convertodml.log
odmltables/gui/graphics/convertodml.pdf
odmltables/gui/graphics/convertodml.ps
odmltables/gui/graphics/convertodml.svg
odmltables/gui/graphics/convertodml.tex
odmltables/gui/graphics/convertodml.tex.backup
odmltables/gui/graphics/createtemplate.aux
odmltables/gui/graphics/createtemplate.dvi
odmltables/gui/graphics/createtemplate.log
odmltables/gui/graphics/createtemplate.pdf
odmltables/gui/graphics/createtemplate.ps
odmltables/gui/graphics/createtemplate.svg
