Metadata-Version: 2.1
Name: odmltables
Version: 1.0.0
Summary: Interface to convert odML structures to and from table-like representations
Home-page: https://github.com/INM-6/python-odmltables
Author: odMLtables authors and contributors
Author-email: j.sprenger@fz-juelich.de
License: BSD
Download-URL: https://github.com/INM-6/python-odmltables/archive/1.0.0.tar.gz
Keywords: odml,excel,metadata management
Platform: UNKNOWN
Classifier: Development Status :: 5 - Production/Stable
Classifier: Intended Audience :: Science/Research
Classifier: License :: OSI Approved :: BSD License
Classifier: Natural Language :: English
Classifier: Operating System :: OS Independent
Classifier: Programming Language :: Python
Classifier: Topic :: Scientific/Engineering
Provides-Extra: test
Provides-Extra: doc
Provides-Extra: gui
